pact.py
python_pact-0.1.1.dist-info/licenses/LICENSE
python_pact-0.1.1.dist-info/METADATA
python_pact-0.1.1.dist-info/WHEEL
python_pact-0.1.1.dist-info/top_level.txt
python_pact-0.1.1.dist-info/RECORD
