Metadata-Version: 2.4
Name: python-pact
Version: 0.1.1
Summary: A lightweight Python metaclass for enforcing required attributes and types in class hierarchies
Author-email: Omer Menashe <unspecified@mail.com>
License: MIT
Project-URL: Source, https://github.com/iamomerm/python-pact
Keywords: python-pact,pact
Classifier: Programming Language :: Python :: 3
Classifier: License :: OSI Approved :: MIT License
Classifier: Operating System :: OS Independent
Requires-Python: >=3.7
License-File: LICENSE
Dynamic: license-file
